salesmanago_tools/__init__.py
salesmanago_tools/service/__init__.py
salesmanago_tools/service/sales_manago_actions.py
salesmanago_tools/utils/__init__.py
salesmanago_tools/utils/constants.py
salesmanago_tools/utils/sales_manago_utils.py
salesmanago_tools/utils/util_funcs.py
salesmanago_tools-0.2.7.dist-info/METADATA
salesmanago_tools-0.2.7.dist-info/WHEEL
salesmanago_tools-0.2.7.dist-info/top_level.txt
salesmanago_tools-0.2.7.dist-info/RECORD
