Metadata-Version: 2.1
Name: salesmanago-tools
Version: 0.2.7
Summary: Salesmanago Tools is a project designed to simplify working with the Salesmanago API
Home-page: https://github.com/Web-parsers/SalesmanagoTools
Author: Kyrylo Pavlenko
Author-email: pavlenkokirill120@gmail.com
Classifier: Programming Language :: Python :: 3
Classifier: License :: OSI Approved :: MIT License
Classifier: Operating System :: OS Independent
Requires-Python: >=3.7
Requires-Dist: aiohttp==3.11.11
Requires-Dist: requests==2.32.3
Requires-Dist: pandas<2.2
